kugl/__init__.py
kugl/api.py
kugl/main.py
kugl/builtins/__init__.py
kugl/builtins/helpers.py
kugl/builtins/resources.py
kugl/builtins/schemas/__init__.py
kugl/builtins/schemas/kubernetes.py
kugl/impl/__init__.py
kugl/impl/config.py
kugl/impl/engine.py
kugl/impl/extract.py
kugl/impl/registry.py
kugl/impl/tables.py
kugl/util/__init__.py
kugl/util/age.py
kugl/util/clock.py
kugl/util/debug.py
kugl/util/misc.py
kugl/util/paths.py
kugl/util/size.py
kugl/util/sqlite.py
kugl/util/sqlparse.py
kugl/builtins/schemas/kubernetes.yaml
kugl-0.6.0.dist-info/METADATA
kugl-0.6.0.dist-info/WHEEL
kugl-0.6.0.dist-info/entry_points.txt
kugl-0.6.0.dist-info/licenses/LICENSE
kugl-0.6.0.dist-info/RECORD
