Metadata-Version: 2.4
Name: kugl
Version: 0.6.0
Summary: Explore Kubernetes resources using SQLite
Project-URL: Homepage, https://github.com/jonross/kugl
Project-URL: Repository, https://github.com/jonross/kugl
Author-email: Jon Ross <kugl.devel@gmail.com>
License: MIT
License-File: LICENSE
Keywords: kubectl,kubernetes,sql,sqlite
Classifier: Development Status :: 3 - Alpha
Classifier: License :: OSI Approved :: MIT License
Classifier: Operating System :: OS Independent
Classifier: Programming Language :: Python :: 3
Classifier: Programming Language :: Python :: 3.9
Classifier: Programming Language :: Python :: 3.10
Classifier: Programming Language :: Python :: 3.11
Classifier: Programming Language :: Python :: 3.12
Classifier: Programming Language :: Python :: 3.13
Classifier: Programming Language :: Python :: 3.14
Requires-Python: >=3.9
Requires-Dist: arrow<=1.3.0,>=1.0.1
Requires-Dist: jmespath<=1.0,>=0.9.5
Requires-Dist: pydantic<=2.9.2,>=2.0.2
Requires-Dist: pyyaml<=6.0.2,>=5.3
Requires-Dist: sqlparse<=0.5.3,>=0.5.1
Requires-Dist: tabulate<=0.9.0,>=0.8.7
